ostree/.gitignore
ostree/__init__.py
ostree/cli.py
ostree/local.py
ostree/oci.py
ostree/remote/__init__.py
ostree/remote/base.py
ostree/remote/docker.py
ostree/tests/conftest.py
ostree/tests/test_cli.py
ostree-0.1.1.dist-info/METADATA
ostree-0.1.1.dist-info/RECORD
ostree-0.1.1.dist-info/WHEEL
ostree-0.1.1.dist-info/entry_points.txt
ostree-0.1.1.dist-info/namespace_packages.txt
ostree-0.1.1.dist-info/top_level.txt
