Metadata-Version: 2.1
Name: ostree
Version: 0.1.1
Summary: Pulls containers and turns them into OS trees for systemd-nspawn.
Home-page: http://github.com/seantis/ostree
Author: Seantis GmbH
Author-email: info@seantis.ch
License: MIT
Platform: any
Classifier: Intended Audience :: Developers
Classifier: Programming Language :: Python
Classifier: Programming Language :: Python :: 3
Classifier: Topic :: Software Development :: Libraries :: Python Modules
Classifier: License :: OSI Approved :: MIT License
Provides-Extra: test
Requires-Dist: cached-property
Requires-Dist: click
Requires-Dist: google-auth
Requires-Dist: requests
Provides-Extra: test
Requires-Dist: coverage; extra == 'test'
Requires-Dist: flake8; extra == 'test'
Requires-Dist: pytest; extra == 'test'
